{
  "DefaultCookiesSetting": 4,
  "DefaultImagesSetting": 1,
  "DefaultJavaScriptSetting": 1,
  "DefaultPluginsSetting": 1,
  "DefaultPopupsSetting": 1,
  "DefaultNotificationsSetting": 2,
  "DefaultGeolocationSetting": 2,
  "DefaultWebBluetoothGuardSetting": 1,
  "DefaultWebUsbGuardSetting": 2,
  "DefaultSearchProviderEnabled": true,
  "DefaultSearchProviderSearchURL": "{google:baseURL}search?q={searchTerms}&{google:RLZ}{google:originalQueryForSuggestion}{google:assistedQueryStats}{google:searchFieldtrialParameter}{google:searchClient}{google:sourceId}ie={inputEncoding}",
  "SystemTimezone": "America/Los_Angeles",
  "EnableMediaRouter": false,
  "EditBookmarksEnabled": false,
  "ExtensionInstallBlacklist": ["*"],
  "ExtensionInstallForcelist": ["cjpalhdlnbpafiamejdnhcphjbkeiagm","pgmjaihnmedpcdkjcgigocogcbffgkbn"],
  "IncognitoModeAvailability": 0,
  "PromotionalTabsEnabled": true,
  "PromptForDownloadLocation": false,
  "RunAllFlashInAllowMode": false,
  "SSLErrorOverrideAllowed": true,
  "SafeBrowsingForTrustedSourcesEnabled": true,
  "SafeSitesFilterBehavior": 1,
  "SavingBrowserHistoryDisabled": false,
  "SearchSuggestEnabled": true,
  "SpellCheckServiceEnabled": true,
  "SpellcheckEnabled": true,
  "SuppressUnsupportedOSWarning": true,
  "SyncDisabled": true,
  "TaskManagerEndProcessEnabled": false,
  "TranslateEnabled": true,
  "UserDataDir": "/tmp",
  "VideoCaptureAllowed": false,
  "ShowAppsShortcutInBookmarkBar": false,
  "ManagedBookmarks": 
  [
  {"toplevel_name": "Websites"}, 
    {"name": "Clever", "url": "clever.com/in/redlands"}, 
		{"name": "Tenmarks", "url": "tenmarks.com"}, 
    {"name": "LexiaCore 5", "url": "lexiacore5.com"},
		{"name": "Google Classroom", "url": "classroom.google.com"}, 
	{"name": "Math", "children": 
		[
		{"name": "Freckle", "url": "classroom.freckle.com"}, 
		{"name": "Prodigy", "url": "prodigygame.com"},
    {"name": "Muliplication", "url": "multiplication.com"},
    {"name": "Math Playground", "url": "mathplayground.com"},
    {"name": "Greg Tang Math", "url": "gregtangmath.com/games"}
		]
	},
   {"name": "Reading", "children": 
      [
	   {"name": "NewsELA", "url": "newsela.com"}, 
	   {"name": "Get Epic", "url": "getepic.com"}
      ]
   }
]
}
